datagovutils/__init__.py
datagovutils/dataset.py
datagovutils-1.0.0.dist-info/METADATA
datagovutils-1.0.0.dist-info/WHEEL
datagovutils-1.0.0.dist-info/top_level.txt
datagovutils-1.0.0.dist-info/RECORD
